opengradient/__init__.py
opengradient/account.py
opengradient/cli.py
opengradient/client.py
opengradient/defaults.py
opengradient/exceptions.py
opengradient/types.py
opengradient/utils.py
opengradient/abi/InferencePrecompile.abi
opengradient/abi/PriceHistoryInference.abi
opengradient/abi/WorkflowScheduler.abi
opengradient/abi/inference.abi
opengradient/alphasense/__init__.py
opengradient/alphasense/read_workflow_tool.py
opengradient/alphasense/run_model_tool.py
opengradient/alphasense/types.py
opengradient/bin/PriceHistoryInference.bin
opengradient/llm/__init__.py
opengradient/llm/og_langchain.py
opengradient/llm/og_openai.py
opengradient/proto/__init__.py
opengradient/proto/infer.proto
opengradient/proto/infer_pb2.py
opengradient/proto/infer_pb2_grpc.py
opengradient/workflow_models/__init__.py
opengradient/workflow_models/constants.py
opengradient/workflow_models/types.py
opengradient/workflow_models/utils.py
opengradient/workflow_models/workflow_models.py
opengradient-0.5.7.dist-info/licenses/LICENSE
opengradient-0.5.7.dist-info/METADATA
opengradient-0.5.7.dist-info/WHEEL
opengradient-0.5.7.dist-info/entry_points.txt
opengradient-0.5.7.dist-info/top_level.txt
opengradient-0.5.7.dist-info/RECORD
