Metadata-Version: 2.4
Name: opengradient
Version: 0.5.7
Summary: Python SDK for OpenGradient decentralized model management & inference services
Author-email: OpenGradient <kyle@vannalabs.ai>
License-Expression: MIT
Project-URL: Homepage, https://opengradient.ai
Classifier: Development Status :: 3 - Alpha
Classifier: Intended Audience :: Developers
Classifier: Programming Language :: Python :: 3.10
Classifier: Programming Language :: Python :: 3.11
Classifier: Programming Language :: Python :: 3.12
Requires-Python: >=3.10
License-File: LICENSE
Requires-Dist: eth-account>=0.13.4
Requires-Dist: web3>=7.3.0
Requires-Dist: click>=8.1.7
Requires-Dist: firebase-rest-api>=1.11.0
Requires-Dist: grpcio>=1.66.2
Requires-Dist: numpy>=1.26.4
Requires-Dist: requests>=2.32.3
Requires-Dist: langchain>=0.3.7
Requires-Dist: openai>=1.58.1
Requires-Dist: pydantic>=2.9.2
Requires-Dist: og-test-x402==0.0.1
Requires-Dist: x402==0.2.1
Dynamic: license-file
